apibean/__init__.py
apibean/notebook/__init__.py
apibean/notebook/_example.py
apibean/notebook/display/_DisplayWriter.py
apibean/notebook/display/_StreamCatcher.py
apibean/notebook/display/_StreamToDeque.py
apibean/notebook/display/__init__.py
apibean/notebook/logtail/__init__.py
apibean/notebook/logtail/tail_log_file.py
apibean/notebook/logtail/tail_log_service.py
apibean/notebook/output/__init__.py
apibean/notebook/runners/_IntervalRunner_CaptureOutput.py
apibean/notebook/runners/_IntervalRunner_StreamCatcher.py
apibean/notebook/runners/__init__.py
apibean/notebook/servers/_EmbeddedAPIServerBase.py
apibean/notebook/servers/_EmbeddedAPIServerDev.py
apibean/notebook/servers/_EmbeddedAPIServerLab.py
apibean/notebook/servers/__init__.py
apibean/notebook/servers/fastapi_server.py
apibean/notebook/servers/fastapi_util.py
apibean/notebook/servers/handlers/AsyncClient.py
apibean/notebook/servers/handlers/RawResponder.py
apibean/notebook/servers/handlers/TestClient.py
apibean/notebook/servers/handlers/__init__.py
apibean/notebook/servers/middlewares/PrettyJSONMiddleware.py
apibean/notebook/servers/middlewares/__init__.py
apibean/notebook/utils/__init__.py
apibean/notebook/utils/net_util.py
apibean/notebook/zmq/__init__.py
apibean/notebook/zmq/base_server.py
apibean/notebook/zmq/base_server_async.py
apibean/notebook/zmq/conf_logger.py
apibean/notebook/zmq/pub_sub_client.py
apibean/notebook/zmq/pub_sub_server.py
apibean/notebook/zmq/pub_sub_server_async.py
apibean/notebook/zmq/push_pull_client.py
apibean/notebook/zmq/push_pull_server.py
apibean/notebook/zmq/push_pull_server_async.py
apibean/notebook/zmq/req_rep_client.py
apibean/notebook/zmq/req_rep_server.py
apibean/notebook/zmq/req_rep_server_async.py
apibean/notebook/zmq/lb/__init__.py
apibean/notebook/zmq/lb/broker.py
apibean/notebook/zmq/lb/client.py
apibean/notebook/zmq/lb/worker.py
apibean_notebook-0.1.0.dist-info/METADATA
apibean_notebook-0.1.0.dist-info/WHEEL
apibean_notebook-0.1.0.dist-info/top_level.txt
apibean_notebook-0.1.0.dist-info/RECORD
