Metadata-Version: 2.4
Name: apibean-notebook
Version: 0.1.0
Summary: Add your description here
Requires-Python: >=3.12
Requires-Dist: asyncio>=3.4.3
Requires-Dist: fastapi<1.0.0,>=0.114.2
Requires-Dist: httpx>=0.28.1
Requires-Dist: ipython>=9.3.0
Requires-Dist: psutil>=7.0.0
Requires-Dist: uvicorn>=0.34.3
